{
	"name": "DynamicFolderDS",
	"properties": {
		"linkedServiceName": {
			"referenceName": "AzureDataLakeStorage2",
			"type": "LinkedServiceReference"
		},
		"parameters": {
			"folder": {
				"type": "string"
			}
		},
		"annotations": [],
		"type": "Json",
		"typeProperties": {
			"location": {
				"type": "AzureBlobFSLocation",
				"folderPath": {
					"value": "@dataset().folder",
					"type": "Expression"
				},
				"fileSystem": "destination"
			}
		},
		"schema": {}
	},
	"type": "Microsoft.DataFactory/factories/datasets"
}